.bumpversion.cfg
CHANGES.txt
MANIFEST.in
README.md
description.rst
development.ini
pip-dev.txt
pip-test.txt
pip.txt
setup.cfg
setup.py
tox.ini
suma/__init__.py
suma/celery.py
suma.egg-info/PKG-INFO
suma.egg-info/SOURCES.txt
suma.egg-info/dependency_links.txt
suma.egg-info/entry_points.txt
suma.egg-info/not-zip-safe
suma.egg-info/requires.txt
suma.egg-info/top_level.txt
suma/api/__init__.py
suma/api/config.py
suma/api/resources.py
suma/api/routes.py
suma/api/views.py
suma/api/schemas/__init__.py
suma/api/schemas/link.py
suma/api/serializers/__init__.py
suma/api/serializers/link.py
suma/api/settings/__init__.py
suma/api/settings/adapter.py
suma/api/settings/celery.py
suma/api/settings/extension.py
suma/api/settings/logger.py
suma/api/settings/service.py
suma/api/subscribers/__init__.py
suma/api/subscribers/request.py
suma/common/__init__.py
suma/common/resources/__init__.py
suma/common/resources/base.py
suma/common/services/__init__.py
suma/common/services/factories.py
suma/core/__init__.py
suma/core/tasks.py
suma/core/migrations/env.py
suma/core/migrations/script.py.mako
suma/core/migrations/versions/INFO
suma/core/models/__init__.py
suma/core/models/link.py
suma/core/models/stat.py
suma/core/models/meta/__init__.py
suma/core/models/meta/base.py
suma/core/models/meta/schema.py
suma/core/models/meta/types.py
suma/core/scripts/__init__.py
suma/core/scripts/initializedb.py
suma/core/services/__init__.py
suma/core/services/file.py
suma/core/services/hashid.py
suma/core/services/link.py
suma/core/services/screenshot.py
suma/core/services/stat.py
suma/core/services/task.py
suma/core/services/interfaces/__init__.py
suma/core/services/interfaces/file.py
suma/core/services/interfaces/hashid.py
suma/core/services/interfaces/link.py
suma/core/services/interfaces/screenshot.py
suma/core/services/interfaces/stat.py
suma/core/services/interfaces/task.py
suma/web/__init__.py
suma/web/config.py
suma/web/resources.py
suma/web/routes.py
suma/web/views.py
suma/web/settings/__init__.py
suma/web/settings/adapter.py
suma/web/settings/celery.py
suma/web/settings/extension.py
suma/web/settings/logger.py
suma/web/settings/service.py