Metadata-Version: 1.1
Name: suma
Version: 0.1.1
Summary: Application to generate short URL's, manage external links and extract link info (eg: title, screenshot, content) 
Home-page: https://github.com/rach/suma
Author: Rachid Belaid
Author-email: rachid.belaid@gmail.com
License: UNKNOWN
Keywords: shorturl screenshot
Platform: UNKNOWN
Classifier: Development Status :: 3 - Alpha
Classifier: Intended Audience :: Developers
Classifier: License :: OSI Approved :: Apache Software License
Classifier: Natural Language :: English
Classifier: Operating System :: OS Independent
Classifier: Programming Language :: Python
Classifier: Programming Language :: Python :: 2.7
Classifier: Framework :: Pyramid
Classifier: Topic :: Internet :: WWW/HTTP
Classifier: Topic :: Internet :: WWW/HTTP :: WSGI :: Application
